xml_stream/__init__.py
xml_stream/_utils.py
xml_stream/data_types.py
xml_stream-0.0.8.dist-info/LICENSE
xml_stream-0.0.8.dist-info/METADATA
xml_stream-0.0.8.dist-info/WHEEL
xml_stream-0.0.8.dist-info/top_level.txt
xml_stream-0.0.8.dist-info/RECORD
