Metadata-Version: 2.1
Name: xml-stream
Version: 0.0.8
Summary: 
Home-page: https://github.com/sopherapps/xml_stream
Author: Martin Ahindura
Author-email: team.sopherapps@gmail.com
License: MIT
Platform: UNKNOWN
Classifier: License :: OSI Approved :: MIT License
Classifier: Programming Language :: Python :: 3
Classifier: Programming Language :: Python :: 3.6
